dalle2_pytorch/__init__.py
dalle2_pytorch/cli.py
dalle2_pytorch/dalle2_pytorch.py
dalle2_pytorch/optimizer.py
dalle2_pytorch/tokenizer.py
dalle2_pytorch/trackers.py
dalle2_pytorch/train_configs.py
dalle2_pytorch/trainer.py
dalle2_pytorch/utils.py
dalle2_pytorch/version.py
dalle2_pytorch/vqgan_vae.py
dalle2_pytorch/vqgan_vae_trainer.py
dalle2_pytorch/data/bpe_simple_vocab_16e6.txt
dalle2_pytorch/dataloaders/__init__.py
dalle2_pytorch/dataloaders/decoder_loader.py
dalle2_pytorch/dataloaders/prior_loader.py
dalle2_pytorch/dataloaders/simple_image_only_dataloader.py
dalle2_pytorch-1.15.6.dist-info/LICENSE
dalle2_pytorch-1.15.6.dist-info/METADATA
dalle2_pytorch-1.15.6.dist-info/WHEEL
dalle2_pytorch-1.15.6.dist-info/entry_points.txt
dalle2_pytorch-1.15.6.dist-info/top_level.txt
dalle2_pytorch-1.15.6.dist-info/RECORD
