Metadata-Version: 2.1
Name: dalle2-pytorch
Version: 1.15.6
Summary: DALL-E 2
Home-page: https://github.com/lucidrains/dalle2-pytorch
Author: Phil Wang
Author-email: lucidrains@gmail.com
License: MIT
Keywords: artificial intelligence,deep learning,text to image
Classifier: Development Status :: 4 - Beta
Classifier: Intended Audience :: Developers
Classifier: Topic :: Scientific/Engineering :: Artificial Intelligence
Classifier: License :: OSI Approved :: MIT License
Classifier: Programming Language :: Python :: 3.6
License-File: LICENSE
Requires-Dist: accelerate
Requires-Dist: click
Requires-Dist: open-clip-torch <3.0.0,>=2.0.0
Requires-Dist: clip-anytorch >=2.5.2
Requires-Dist: coca-pytorch >=0.0.5
Requires-Dist: ema-pytorch >=0.0.7
Requires-Dist: einops >=0.7.0
Requires-Dist: embedding-reader
Requires-Dist: kornia >=0.5.4
Requires-Dist: numpy
Requires-Dist: packaging
Requires-Dist: pillow
Requires-Dist: pydantic >=2
Requires-Dist: pytorch-warmup
Requires-Dist: resize-right >=0.0.2
Requires-Dist: rotary-embedding-torch
Requires-Dist: torch >=1.10
Requires-Dist: torchvision
Requires-Dist: tqdm
Requires-Dist: vector-quantize-pytorch
Requires-Dist: x-clip >=0.4.4
Requires-Dist: webdataset >=0.2.5
Requires-Dist: fsspec >=2022.1.0
Requires-Dist: torchmetrics[image] >=0.8.0
